README.md
setup.py
elonet_formation_4/__init__.py
elonet_formation_4/operations.py
elonet_formation_4.egg-info/PKG-INFO
elonet_formation_4.egg-info/SOURCES.txt
elonet_formation_4.egg-info/dependency_links.txt
elonet_formation_4.egg-info/requires.txt
elonet_formation_4.egg-info/top_level.txt