Metadata-Version: 1.0
Name: elonet-formation-4
Version: 0.0.1
Summary: Demonstration de creation d'un package Python
Home-page: https://elonet.github.io/python3_formation_4/
Author: Rasta dev
Author-email: arthur@elonet.fr
License: UNKNOWN
Platform: UNKNOWN
